tap_hubspot/__init__.py
tap_hubspot/schemas/campaigns.json
tap_hubspot/schemas/companies.json
tap_hubspot/schemas/contact_lists.json
tap_hubspot/schemas/contacts.json
tap_hubspot/schemas/contacts_by_company.json
tap_hubspot/schemas/deal_pipelines.json
tap_hubspot/schemas/deals.json
tap_hubspot/schemas/email_events.json
tap_hubspot/schemas/engagements.json
tap_hubspot/schemas/forms.json
tap_hubspot/schemas/owners.json
tap_hubspot/schemas/subscription_changes.json
tap_hubspot/schemas/tickets.json
tap_hubspot/schemas/versions.json
tap_hubspot/schemas/workflows.json
singer_tap_hubspot_cv-2.12.5.dist-info/LICENSE
singer_tap_hubspot_cv-2.12.5.dist-info/METADATA
singer_tap_hubspot_cv-2.12.5.dist-info/WHEEL
singer_tap_hubspot_cv-2.12.5.dist-info/entry_points.txt
singer_tap_hubspot_cv-2.12.5.dist-info/top_level.txt
singer_tap_hubspot_cv-2.12.5.dist-info/RECORD
