Metadata-Version: 2.1
Name: singer-tap-hubspot-cv
Version: 2.12.5
Summary: Singer.io tap for extracting data from the HubSpot API
Home-page: http://singer.io
Author: Stitch
Classifier: Programming Language :: Python :: 3 :: Only
License-File: LICENSE
Requires-Dist: attrs ==16.3.0
Requires-Dist: singer-python ==5.13.0
Requires-Dist: requests ==2.20.0
Requires-Dist: backoff ==1.8.0
Requires-Dist: requests-mock ==1.3.0
Provides-Extra: dev
Requires-Dist: pylint ==2.5.3 ; extra == 'dev'
Requires-Dist: nose ==1.3.7 ; extra == 'dev'
